foambryo/__init__.py
foambryo/curvature.py
foambryo/dcel.py
foambryo/force_inference.py
foambryo/geometry.py
foambryo/io.py
foambryo/plotting_utilities.py
foambryo/pressure_inference.py
foambryo/tension_inference.py
foambryo/viewing.py
foambryo-0.3.5.dist-info/METADATA
foambryo-0.3.5.dist-info/WHEEL
foambryo-0.3.5.dist-info/top_level.txt
foambryo-0.3.5.dist-info/RECORD
