Metadata-Version: 2.1
Name: foambryo
Version: 0.3.5
Summary: Tension inference for 3D cell assemblies
Home-page: https://github.com/sacha-ichbiah/foambryo
Author: Sacha Ichbiah
Author-email: sacha.ichbiah@college-de-france.fr
License: CC BY-NC-SA 4.0
Project-URL: Team website, https://www.turlierlab.com/
Classifier: Programming Language :: Python :: 3
Classifier: Operating System :: POSIX :: Linux
Classifier: Operating System :: MacOS
Classifier: Intended Audience :: Science/Research
Requires-Python: >=3.6
Requires-Dist: delaunay-watershed-3d >=0.3.1
Requires-Dist: networkx >=2.5.1
Requires-Dist: numpy >=1.21.6
Requires-Dist: scipy >=1.4.1
Requires-Dist: torch >=2.2.0
Requires-Dist: trimesh >=3.8.12
Provides-Extra: viewing
Requires-Dist: polyscope >=1.2.0 ; extra == 'viewing'
Requires-Dist: matplotlib >=3.3.1 ; extra == 'viewing'
